{
  "policies": {
    "DisableFirefoxStudies": true,
    "DisablePocket": true,
    "DisableTelemetry": true,
    "DontCheckDefaultBrowser": true,
    "ExtensionSettings": {
      "jid1-BoFifL9Vbdl2zQ@jetpack": {
        "installation_mode": "normal_installed",
        "private_browsing": true,
        "install_url": "https://addons.mozilla.org/firefox/downloads/latest/decentraleyes/latest.xpi"
      },
      "78272b6fa58f4a1abaac99321d503a20@proton.me": {
        "installation_mode": "normal_installed",
        "private_browsing": true,
        "install_url": "https://addons.mozilla.org/firefox/downloads/latest/proton-pass/latest.xpi"
      },
      "vpn@proton.ch": {
        "installation_mode": "normal_installed",
        "private_browsing": true,
        "install_url": "https://addons.mozilla.org/firefox/downloads/latest/proton-vpn-firefox-extension/latest.xpi"
      },
      "pywalfox@frewacom.org": {
        "installation_mode": "normal_installed",
        "private_browsing": true,
        "install_url": "https://addons.mozilla.org/firefox/downloads/latest/pywalfox/latest.xpi"
      },
      "search@kagi.com": {
        "installation_mode": "normal_installed",
        "private_browsing": true,
        "install_url": "https://addons.mozilla.org/firefox/downloads/latest/kagi-search-for-firefox/latest.xpi"
      },
      "{7a7a4a92-a2a0-41d1-9fd7-1e92480d612d}": {
        "installation_mode": "normal_installed",
        "private_browsing": true,
        "install_url": "https://addons.mozilla.org/firefox/downloads/latest/styl-us/latest.xpi"
      },
      "firefox@tampermonkey.net": {
        "installation_mode": "normal_installed",
        "private_browsing": true,
        "install_url": "https://addons.mozilla.org/firefox/downloads/latest/tampermonkey/latest.xpi"
      },
      "uBlock0@raymondhill.net": {
        "installation_mode": "normal_installed",
        "private_browsing": true,
        "install_url": "https://addons.mozilla.org/firefox/downloads/latest/ublock-origin/latest.xpi"
      }
    },
    "FirefoxHome": {
      "Highlights": false,
      "Locked": false,
      "Pocket": false,
      "Snippets": false,
      "SponsoredPocket": false,
      "SponsoredStories": false,
      "SponsoredTopSites": false,
      "Stories": false
    },
    "Homepage": {
      "Locked": false,
      "StartPage": "none",
      "URL": "about:blank"
    },
    "FirefoxSuggest": {
      "ImproveSuggest": false,
      "Locked": false,
      "SponsoredSuggestions": false,
      "WebSuggestions": false
    },
    "ManualAppUpdateOnly": true,
    "NoDefaultBookmarks": true,
    "OfferToSaveLoginsDefault": false,
    "OverrideFirstRunPage": "",
    "OverridePostUpdatePage": "",
    "SearchEngines": {
      "Default": "DuckDuckGo",
      "PreventInstalls": true
    },
    "SearchSuggestEnabled": false,
    "SkipTermsOfUse": true,
    "UserMessaging": {
      "ExtensionRecommendations": false,
      "FeatureRecommendations": false,
      "FirefoxLabs": false,
      "Locked": false,
      "MoreFromMozilla": false,
      "SkipOnboarding": true,
      "UrlbarInterventions": false
    }
  }
}
